README
setup.py
guidb/__init__.py
guidb/client.py
guidb/guidb_server.py
guidb/query_pb2.py
guidb/server.py
guidb/test.py
guidb.egg-info/PKG-INFO
guidb.egg-info/SOURCES.txt
guidb.egg-info/dependency_links.txt
guidb.egg-info/requires.txt
guidb.egg-info/top_level.txt