Metadata-Version: 1.1
Name: guidb
Version: 0.1.5
Summary: Very simple parallel database based on leveldb and zeromq.
Home-page: http://guillemborrell.es
Author: Guillem Borrell
Author-email: guillemborrell@gmail.com
License: BSD
Keywords: parallel database
Platform: UNKNOWN
Classifier: Development Status :: 3 - Alpha
Classifier: Topic :: Utilities
Classifier: Programming Language :: Python :: 2.7
Classifier: Intended Audience :: Developers
Classifier: License :: OSI Approved :: BSD License
